{
  "version": 1,
  "tasks": [
    {
      "id": "TASK-0001",
      "title": "EP-A Data Model v2 + Compatibility Layer",
      "status": "Backlog",
      "owner": "sentinel",
      "due_date": null,
      "priority": "P0",
      "tags": [
        "epic",
        "presentation-v2",
        "phase-1"
      ],
      "linked_refs": [
        "PSv2"
      ],
      "description": "Define DeckSpec v2 and SlideSpec v2, including legacy mapping from v1 fields. Acceptance: existing v1 flows still run under feature flag off.",
      "comments": [],
      "request_approval": null,
      "created_at": "2026-02-26T22:40:42Z",
      "updated_at": "2026-02-27T19:37:21.367Z",
      "created_by": "sentinel",
      "updated_by": "isaac"
    },
    {
      "id": "TASK-0002",
      "title": "ST-A1 Create DeckSpec v2 persistence + load by selectors",
      "status": "Backlog",
      "owner": "sentinel",
      "due_date": null,
      "priority": "P0",
      "tags": [
        "story",
        "epic:EP-A",
        "api"
      ],
      "linked_refs": [
        "GET /api/presentation-studio/decks"
      ],
      "description": "Persist deckId, initiativeId, buyerId, deckType, template theme, providers, savepoint pointer. Acceptance: deck loads by initiativeId/deckType/buyerId.",
      "comments": [],
      "request_approval": null,
      "created_at": "2026-02-26T22:40:42Z",
      "updated_at": "2026-02-27T19:37:37.242Z",
      "created_by": "sentinel",
      "updated_by": "isaac"
    },
    {
      "id": "TASK-0003",
      "title": "ST-A2 Upgrade SlideSpec to slot-aware v2",
      "status": "Backlog",
      "owner": "sentinel",
      "due_date": null,
      "priority": "P0",
      "tags": [
        "story",
        "epic:EP-A",
        "slides"
      ],
      "linked_refs": [
        "PATCH /api/presentation-studio/decks/{deckId}/slides/{slideId}"
      ],
      "description": "Add templateId, slots, constraints, imagePlans, qa, pipeline fields. Map legacy title/bullets/imagePrompt/layout into slots/templateId.",
      "comments": [],
      "request_approval": null,
      "created_at": "2026-02-26T22:40:42Z",
      "updated_at": "2026-02-26T22:40:42Z",
      "created_by": "sentinel",
      "updated_by": "sentinel"
    },
    {
      "id": "TASK-0004",
      "title": "EP-B Presentation Studio API Surface (Phase 1)",
      "status": "Backlog",
      "owner": "sentinel",
      "due_date": null,
      "priority": "P0",
      "tags": [
        "epic",
        "presentation-v2",
        "api"
      ],
      "linked_refs": [
        "PSv2 APIs"
      ],
      "description": "Implement minimal deck/slides/templates/savepoints/pipeline status routes for v2.",
      "comments": [],
      "request_approval": null,
      "created_at": "2026-02-26T22:40:42Z",
      "updated_at": "2026-02-26T22:40:42Z",
      "created_by": "sentinel",
      "updated_by": "sentinel"
    },
    {
      "id": "TASK-0005",
      "title": "ST-B1 Add Deck APIs (GET/POST/PATCH)",
      "status": "Backlog",
      "owner": "sentinel",
      "due_date": null,
      "priority": "P0",
      "tags": [
        "story",
        "epic:EP-B",
        "api"
      ],
      "linked_refs": [
        "/api/presentation-studio/decks"
      ],
      "description": "Create/read/update deck metadata and current save point. Acceptance: selector-driven load works from UI.",
      "comments": [],
      "request_approval": null,
      "created_at": "2026-02-26T22:40:42Z",
      "updated_at": "2026-02-26T22:40:42Z",
      "created_by": "sentinel",
      "updated_by": "sentinel"
    },
    {
      "id": "TASK-0006",
      "title": "ST-B2 Add Slides APIs (list/get/create/update/delete)",
      "status": "Backlog",
      "owner": "sentinel",
      "due_date": null,
      "priority": "P0",
      "tags": [
        "story",
        "epic:EP-B",
        "slides"
      ],
      "linked_refs": [
        "/api/presentation-studio/decks/{deckId}/slides"
      ],
      "description": "CRUD slide specs in deck order with re-render hooks. Acceptance: single-slide update without full regen.",
      "comments": [],
      "request_approval": null,
      "created_at": "2026-02-26T22:40:42Z",
      "updated_at": "2026-02-26T22:40:42Z",
      "created_by": "sentinel",
      "updated_by": "sentinel"
    },
    {
      "id": "TASK-0007",
      "title": "EP-C Template Library + Assignment",
      "status": "Backlog",
      "owner": "sentinel",
      "due_date": null,
      "priority": "P1",
      "tags": [
        "epic",
        "presentation-v2",
        "templates"
      ],
      "linked_refs": [
        "TemplateLibrary"
      ],
      "description": "Ship canonical templates with slot schemas and API reads.",
      "comments": [],
      "request_approval": null,
      "created_at": "2026-02-26T22:40:42Z",
      "updated_at": "2026-02-26T22:40:42Z",
      "created_by": "sentinel",
      "updated_by": "sentinel"
    },
    {
      "id": "TASK-0008",
      "title": "ST-C1 Define 8 canonical templates + slots schema",
      "status": "Backlog",
      "owner": "sentinel",
      "due_date": null,
      "priority": "P1",
      "tags": [
        "story",
        "epic:EP-C",
        "templates"
      ],
      "linked_refs": [
        "GET /api/presentation-studio/templates"
      ],
      "description": "cover-hero, two-col-bullets, feature-grid, layered-diagram, flywheel, comparison-matrix, timeline, closing-cta.",
      "comments": [],
      "request_approval": null,
      "created_at": "2026-02-26T22:40:42Z",
      "updated_at": "2026-02-26T22:40:42Z",
      "created_by": "sentinel",
      "updated_by": "sentinel"
    },
    {
      "id": "TASK-0009",
      "title": "EP-D Save Points + Restore",
      "status": "Backlog",
      "owner": "sentinel",
      "due_date": null,
      "priority": "P1",
      "tags": [
        "epic",
        "presentation-v2",
        "savepoints"
      ],
      "linked_refs": [
        "/api/presentation-studio/decks/{deckId}/savepoints"
      ],
      "description": "Create/list/restore save points with frozen DeckSpec/SlideSpecs and render refs.",
      "comments": [],
      "request_approval": null,
      "created_at": "2026-02-26T22:40:42Z",
      "updated_at": "2026-02-26T22:40:42Z",
      "created_by": "sentinel",
      "updated_by": "sentinel"
    },
    {
      "id": "TASK-0010",
      "title": "EP-E Studio UI v2 Shell (feature-flagged)",
      "status": "Backlog",
      "owner": "sentinel",
      "due_date": null,
      "priority": "P1",
      "tags": [
        "epic",
        "presentation-v2",
        "ui"
      ],
      "linked_refs": [
        "/dashboard/initiative/:id"
      ],
      "description": "Add DeckContextBar, ModePanel (AI Slides/Team Chat), Source/QA tabs and bottom command bar while preserving v1 paths.",
      "comments": [],
      "request_approval": null,
      "created_at": "2026-02-26T22:40:42Z",
      "updated_at": "2026-02-26T22:40:42Z",
      "created_by": "sentinel",
      "updated_by": "sentinel"
    },
    {
      "id": "TASK-0011",
      "title": "EP-F Pipeline Status + AI Edit loop",
      "status": "Backlog",
      "owner": "sentinel",
      "due_date": null,
      "priority": "P1",
      "tags": [
        "epic",
        "presentation-v2",
        "pipeline"
      ],
      "linked_refs": [
        "POST /api/presentation-studio/decks/{deckId}/pipeline/run"
      ],
      "description": "Enable slide/deck run + status polling + targeted instruction application (critique->rewrite->render->qa).",
      "comments": [],
      "request_approval": null,
      "created_at": "2026-02-26T22:40:42Z",
      "updated_at": "2026-02-26T22:40:42Z",
      "created_by": "sentinel",
      "updated_by": "sentinel"
    },
    {
      "id": "TASK-0012",
      "title": "EP-G Signal Register v1 for pressure tracking",
      "status": "Backlog",
      "owner": "sentinel",
      "due_date": null,
      "priority": "P1",
      "tags": [
        "epic",
        "dashboard",
        "signals"
      ],
      "linked_refs": [
        "Pressure Surface"
      ],
      "description": "Track Monitor/Verified/Actioned signals with sources, confidence, buyer/initiative links, and deck handoff hook.",
      "comments": [],
      "request_approval": null,
      "created_at": "2026-02-26T22:40:42Z",
      "updated_at": "2026-02-26T22:40:42Z",
      "created_by": "sentinel",
      "updated_by": "sentinel"
    },
    {
      "id": "TASK-0013",
      "title": "US-A1 As an editor, I can load a deck by initiative/deck selectors",
      "status": "Backlog",
      "owner": "sentinel",
      "due_date": null,
      "priority": "P0",
      "tags": [
        "story",
        "epic:EP-A",
        "user-story"
      ],
      "linked_refs": [
        "EP-A",
        "selectors"
      ],
      "description": "Story under EP-A: selector-based deck retrieval returns a stable DeckSpec v2 object.",
      "comments": [],
      "request_approval": null,
      "created_at": "2026-02-26T22:48:00Z",
      "updated_at": "2026-02-26T22:48:00Z",
      "created_by": "sentinel",
      "updated_by": "sentinel"
    },
    {
      "id": "TASK-0014",
      "title": "TS-A1.1 Create DeckSpec v2 schema + defaults",
      "status": "Ready for Review",
      "owner": "sentinel",
      "due_date": null,
      "priority": "P0",
      "tags": [
        "task",
        "epic:EP-A",
        "story:US-A1"
      ],
      "linked_refs": [
        "schema",
        "deckspec-v2"
      ],
      "description": "Define deckId, initiativeId, buyerId, deckType, theme, providers, slideOrder, savepoint pointer.",
      "comments": [
        {
          "id": "note-0014-1",
          "author": "sentinel",
          "text": "Implemented DeckSpec v2 schema + default store scaffolding in admin server. Added schema/data files bootstrap at startup.",
          "created_at": "2026-02-28T23:56:00Z"
        }
      ],
      "request_approval": null,
      "created_at": "2026-02-26T22:48:00Z",
      "updated_at": "2026-02-28T23:56:00Z",
      "created_by": "sentinel",
      "updated_by": "sentinel"
    },
    {
      "id": "TASK-0015",
      "title": "TS-A1.2 Implement deck resolver by selectors",
      "status": "In Progress",
      "owner": "sentinel",
      "due_date": null,
      "priority": "P0",
      "tags": [
        "task",
        "epic:EP-A",
        "story:US-A1"
      ],
      "linked_refs": [
        "resolver",
        "compatibility"
      ],
      "description": "Load/create DeckSpec using initiativeId+deckType+buyerId; preserve v1 fallback behavior.",
      "comments": [],
      "request_approval": null,
      "created_at": "2026-02-26T22:48:00Z",
      "updated_at": "2026-02-27T23:24:00Z",
      "created_by": "sentinel",
      "updated_by": "sentinel"
    },
    {
      "id": "TASK-0016",
      "title": "US-A2 As an editor, I can edit legacy slide fields without breaking v2",
      "status": "Backlog",
      "owner": "sentinel",
      "due_date": null,
      "priority": "P0",
      "tags": [
        "story",
        "epic:EP-A",
        "user-story"
      ],
      "linked_refs": [
        "EP-A",
        "slidespec-v2"
      ],
      "description": "Story under EP-A: legacy title/bullets/imagePrompt map safely into SlideSpec v2 slots/templateId.",
      "comments": [],
      "request_approval": null,
      "created_at": "2026-02-26T22:48:00Z",
      "updated_at": "2026-02-26T22:48:00Z",
      "created_by": "sentinel",
      "updated_by": "sentinel"
    },
    {
      "id": "TASK-0017",
      "title": "TS-A2.1 Add SlideSpec v2 mapper (legacy->slots)",
      "status": "In Progress",
      "owner": "sentinel",
      "due_date": null,
      "priority": "P0",
      "tags": [
        "task",
        "epic:EP-A",
        "story:US-A2"
      ],
      "linked_refs": [
        "mapper",
        "legacy-compat"
      ],
      "description": "Implement mapping layout->templateId and legacy fields to slots structure.",
      "comments": [],
      "request_approval": null,
      "created_at": "2026-02-26T22:48:00Z",
      "updated_at": "2026-02-27T23:24:00Z",
      "created_by": "sentinel",
      "updated_by": "sentinel"
    },
    {
      "id": "TASK-0018",
      "title": "TS-A2.2 Persist pipeline/qa/render metadata on slide records",
      "status": "Backlog",
      "owner": "sentinel",
      "due_date": null,
      "priority": "P1",
      "tags": [
        "task",
        "epic:EP-A",
        "story:US-A2"
      ],
      "linked_refs": [
        "pipeline",
        "qa",
        "render"
      ],
      "description": "Add pipeline stage state, qa flags/score, rendered refs; keep optional for old slides.",
      "comments": [],
      "request_approval": null,
      "created_at": "2026-02-26T22:48:00Z",
      "updated_at": "2026-02-26T22:48:00Z",
      "created_by": "sentinel",
      "updated_by": "sentinel"
    },
    {
      "id": "TASK-0019",
      "title": "US-B1 As a user, I can manage deck records via API",
      "status": "Backlog",
      "owner": "sentinel",
      "due_date": null,
      "priority": "P0",
      "tags": [
        "story",
        "epic:EP-B",
        "user-story"
      ],
      "linked_refs": [
        "EP-B",
        "api:decks"
      ],
      "description": "Story under EP-B: create/get/update deck metadata via presentation-studio endpoints.",
      "comments": [],
      "request_approval": null,
      "created_at": "2026-02-26T22:48:00Z",
      "updated_at": "2026-02-26T22:48:00Z",
      "created_by": "sentinel",
      "updated_by": "sentinel"
    },
    {
      "id": "TASK-0020",
      "title": "TS-B1.1 Implement GET/POST /api/presentation-studio/decks",
      "status": "In Progress",
      "owner": "sentinel",
      "due_date": null,
      "priority": "P0",
      "tags": [
        "task",
        "epic:EP-B",
        "story:US-B1"
      ],
      "linked_refs": [
        "GET/POST decks"
      ],
      "description": "Add list/create with selector filters and validation.",
      "comments": [],
      "request_approval": null,
      "created_at": "2026-02-26T22:48:00Z",
      "updated_at": "2026-02-27T23:24:00Z",
      "created_by": "sentinel",
      "updated_by": "sentinel"
    },
    {
      "id": "TASK-0021",
      "title": "TS-B1.2 Implement PATCH /api/presentation-studio/decks/{deckId}",
      "status": "In Progress",
      "owner": "sentinel",
      "due_date": null,
      "priority": "P0",
      "tags": [
        "task",
        "epic:EP-B",
        "story:US-B1"
      ],
      "linked_refs": [
        "PATCH decks"
      ],
      "description": "Update styleMode/providers/globalTemplateTheme/currentSavePointId.",
      "comments": [],
      "request_approval": null,
      "created_at": "2026-02-26T22:48:00Z",
      "updated_at": "2026-02-27T23:24:00Z",
      "created_by": "sentinel",
      "updated_by": "sentinel"
    },
    {
      "id": "TASK-0022",
      "title": "US-B2 As a user, I can CRUD slides in a deck via API",
      "status": "Backlog",
      "owner": "sentinel",
      "due_date": null,
      "priority": "P0",
      "tags": [
        "story",
        "epic:EP-B",
        "user-story"
      ],
      "linked_refs": [
        "EP-B",
        "api:slides"
      ],
      "description": "Story under EP-B: slide-level operations support add/edit/delete without full regen.",
      "comments": [],
      "request_approval": null,
      "created_at": "2026-02-26T22:48:00Z",
      "updated_at": "2026-02-26T22:48:00Z",
      "created_by": "sentinel",
      "updated_by": "sentinel"
    },
    {
      "id": "TASK-0023",
      "title": "TS-B2.1 Implement slide list/get endpoints",
      "status": "Backlog",
      "owner": "sentinel",
      "due_date": null,
      "priority": "P0",
      "tags": [
        "task",
        "epic:EP-B",
        "story:US-B2"
      ],
      "linked_refs": [
        "GET slides"
      ],
      "description": "GET deck slides + GET single slide by slideId.",
      "comments": [],
      "request_approval": null,
      "created_at": "2026-02-26T22:48:00Z",
      "updated_at": "2026-02-26T22:48:00Z",
      "created_by": "sentinel",
      "updated_by": "sentinel"
    },
    {
      "id": "TASK-0024",
      "title": "TS-B2.2 Implement slide create/update/delete endpoints",
      "status": "Backlog",
      "owner": "sentinel",
      "due_date": null,
      "priority": "P0",
      "tags": [
        "task",
        "epic:EP-B",
        "story:US-B2"
      ],
      "linked_refs": [
        "mutations",
        "slide-order"
      ],
      "description": "POST/PATCH/DELETE slide endpoints with order maintenance.",
      "comments": [],
      "request_approval": null,
      "created_at": "2026-02-26T22:48:00Z",
      "updated_at": "2026-02-26T22:48:00Z",
      "created_by": "sentinel",
      "updated_by": "sentinel"
    },
    {
      "id": "TASK-0025",
      "title": "US-B3 As a user, I can fetch templates and savepoints via API",
      "status": "Backlog",
      "owner": "sentinel",
      "due_date": null,
      "priority": "P1",
      "tags": [
        "story",
        "epic:EP-B",
        "user-story"
      ],
      "linked_refs": [
        "EP-B",
        "api:templates",
        "api:savepoints"
      ],
      "description": "Story under EP-B: template list/detail and savepoint list/create/restore endpoints available.",
      "comments": [],
      "request_approval": null,
      "created_at": "2026-02-26T22:48:00Z",
      "updated_at": "2026-02-26T22:48:00Z",
      "created_by": "sentinel",
      "updated_by": "sentinel"
    },
    {
      "id": "TASK-0026",
      "title": "TS-B3.1 Implement template list/detail endpoints",
      "status": "Backlog",
      "owner": "sentinel",
      "due_date": null,
      "priority": "P1",
      "tags": [
        "task",
        "epic:EP-B",
        "story:US-B3"
      ],
      "linked_refs": [
        "templates-api"
      ],
      "description": "GET /templates and /templates/{templateId}.",
      "comments": [],
      "request_approval": null,
      "created_at": "2026-02-26T22:48:00Z",
      "updated_at": "2026-02-26T22:48:00Z",
      "created_by": "sentinel",
      "updated_by": "sentinel"
    },
    {
      "id": "TASK-0027",
      "title": "TS-B3.2 Implement savepoint list/create/restore endpoints",
      "status": "Backlog",
      "owner": "sentinel",
      "due_date": null,
      "priority": "P1",
      "tags": [
        "task",
        "epic:EP-B",
        "story:US-B3"
      ],
      "linked_refs": [
        "savepoints-api"
      ],
      "description": "GET/POST savepoints and POST restore by savePointId.",
      "comments": [],
      "request_approval": null,
      "created_at": "2026-02-26T22:48:00Z",
      "updated_at": "2026-02-26T22:48:00Z",
      "created_by": "sentinel",
      "updated_by": "sentinel"
    },
    {
      "id": "TASK-0028",
      "title": "US-UI1 Replace board edit modal with persistent right-side detail panel",
      "status": "Backlog",
      "owner": "sentinel",
      "due_date": null,
      "priority": "P1",
      "tags": [
        "story",
        "board-ui",
        "epic:EP-E",
        "user-story"
      ],
      "linked_refs": [
        "board",
        "task-detail-panel"
      ],
      "description": "Swap modal editing for a non-blocking side panel with full task fields (title, description, acceptance, tags, links, comments, status, owner, priority) and inline save actions.",
      "comments": [],
      "request_approval": null,
      "created_at": "2026-02-26T22:55:00Z",
      "updated_at": "2026-02-26T22:55:00Z",
      "created_by": "sentinel",
      "updated_by": "sentinel"
    },
    {
      "id": "TASK-0029",
      "title": "TS-UI1.1 Implement board task detail drawer component + route/state binding",
      "status": "Backlog",
      "owner": "sentinel",
      "due_date": null,
      "priority": "P1",
      "tags": [
        "task",
        "board-ui",
        "story:US-UI1"
      ],
      "linked_refs": [
        "/dashboard/board"
      ],
      "description": "Add right-side drawer panel opened by task click; preserve board context; support keyboard close and mobile collapse.",
      "comments": [],
      "request_approval": null,
      "created_at": "2026-02-26T22:55:00Z",
      "updated_at": "2026-02-26T22:55:00Z",
      "created_by": "sentinel",
      "updated_by": "sentinel"
    },
    {
      "id": "TASK-0030",
      "title": "TS-UI1.2 Wire drawer form fields to existing task update APIs + validation",
      "status": "Backlog",
      "owner": "sentinel",
      "due_date": null,
      "priority": "P1",
      "tags": [
        "task",
        "board-ui",
        "story:US-UI1"
      ],
      "linked_refs": [
        "task update api"
      ],
      "description": "Bind all editable fields and save actions; keep audit logging and governance checks unchanged.",
      "comments": [],
      "request_approval": null,
      "created_at": "2026-02-26T22:55:00Z",
      "updated_at": "2026-02-26T22:55:00Z",
      "created_by": "sentinel",
      "updated_by": "sentinel"
    },
    {
      "id": "TASK-0031",
      "title": "US-A3 Pipeline Engine (slide + deck runs)",
      "status": "Backlog",
      "owner": "sentinel",
      "due_date": null,
      "priority": "P0",
      "tags": [
        "story",
        "epic:EP-A",
        "user-story"
      ],
      "linked_refs": [
        "pipeline/run",
        "pipeline/status"
      ],
      "description": "Acceptance: run by scope, stage status persisted, QA updated after run. Dependencies: US-A1, US-A2.",
      "comments": [],
      "request_approval": null,
      "created_at": "2026-02-26T23:20:00Z",
      "updated_at": "2026-02-26T23:20:00Z",
      "created_by": "sentinel",
      "updated_by": "sentinel"
    },
    {
      "id": "TASK-0032",
      "title": "TS-A3.1 Implement pipeline run endpoint with persisted runId",
      "status": "Backlog",
      "owner": "sentinel",
      "due_date": null,
      "priority": "P0",
      "tags": [
        "task",
        "epic:EP-A",
        "story:US-A3"
      ],
      "linked_refs": [
        "POST /api/presentation-studio/decks/{deckId}/pipeline/run"
      ],
      "description": "Implement POST /api/presentation-studio/decks/{deckId}/pipeline/run with stages plan,draft,critique,rewrite,render,qa; scope deck|slide.",
      "comments": [],
      "request_approval": null,
      "created_at": "2026-02-26T23:20:00Z",
      "updated_at": "2026-02-26T23:20:00Z",
      "created_by": "sentinel",
      "updated_by": "sentinel"
    },
    {
      "id": "TASK-0033",
      "title": "US-A4 SavePoint versioning and restore",
      "status": "Backlog",
      "owner": "sentinel",
      "due_date": null,
      "priority": "P0",
      "tags": [
        "story",
        "epic:EP-A",
        "user-story"
      ],
      "linked_refs": [
        "savepoints"
      ],
      "description": "Acceptance: create/list/restore savepoints; restore updates preview atomically.",
      "comments": [],
      "request_approval": null,
      "created_at": "2026-02-26T23:20:00Z",
      "updated_at": "2026-02-26T23:20:00Z",
      "created_by": "sentinel",
      "updated_by": "sentinel"
    },
    {
      "id": "TASK-0034",
      "title": "TS-A4.1 Implement savepoint create/list/restore APIs",
      "status": "Backlog",
      "owner": "sentinel",
      "due_date": null,
      "priority": "P0",
      "tags": [
        "task",
        "epic:EP-A",
        "story:US-A4"
      ],
      "linked_refs": [
        "POST /savepoints",
        "GET /savepoints",
        "POST /savepoints/{id}/restore"
      ],
      "description": "POST/GET savepoints and POST restore; immutable snapshot refs for DeckSpec+SlideSpec+render.",
      "comments": [],
      "request_approval": null,
      "created_at": "2026-02-26T23:20:00Z",
      "updated_at": "2026-02-26T23:20:00Z",
      "created_by": "sentinel",
      "updated_by": "sentinel"
    },
    {
      "id": "TASK-0035",
      "title": "US-B1 AI Slides mode panel and instruction loop",
      "status": "Backlog",
      "owner": "sentinel",
      "due_date": null,
      "priority": "P1",
      "tags": [
        "story",
        "epic:EP-B",
        "user-story"
      ],
      "linked_refs": [
        "ModePanel",
        "AICommandInput"
      ],
      "description": "Acceptance: AI Slides tab visible, instruction input triggers pipeline, styleMode persists.",
      "comments": [],
      "request_approval": null,
      "created_at": "2026-02-26T23:20:00Z",
      "updated_at": "2026-02-26T23:20:00Z",
      "created_by": "sentinel",
      "updated_by": "sentinel"
    },
    {
      "id": "TASK-0036",
      "title": "TS-B1.1 Add AI command input + style toggle wiring",
      "status": "Backlog",
      "owner": "sentinel",
      "due_date": null,
      "priority": "P1",
      "tags": [
        "task",
        "epic:EP-B",
        "story:US-B1"
      ],
      "linked_refs": [
        "PATCH /api/presentation-studio/decks/{deckId}"
      ],
      "description": "Route instruction to pipeline run; persist DeckSpec.styleMode professional|creative.",
      "comments": [],
      "request_approval": null,
      "created_at": "2026-02-26T23:20:00Z",
      "updated_at": "2026-02-26T23:20:00Z",
      "created_by": "sentinel",
      "updated_by": "sentinel"
    },
    {
      "id": "TASK-0037",
      "title": "US-B2 Team Chat per deck",
      "status": "Backlog",
      "owner": "sentinel",
      "due_date": null,
      "priority": "P1",
      "tags": [
        "story",
        "epic:EP-B",
        "user-story"
      ],
      "linked_refs": [
        "team-chat"
      ],
      "description": "Acceptance: chat messages persist per deck and support optional slide references.",
      "comments": [],
      "request_approval": null,
      "created_at": "2026-02-26T23:20:00Z",
      "updated_at": "2026-02-26T23:20:00Z",
      "created_by": "sentinel",
      "updated_by": "sentinel"
    },
    {
      "id": "TASK-0038",
      "title": "TS-B2.1 Implement TeamChatThread model + message APIs",
      "status": "Backlog",
      "owner": "sentinel",
      "due_date": null,
      "priority": "P1",
      "tags": [
        "task",
        "epic:EP-B",
        "story:US-B2"
      ],
      "linked_refs": [
        "GET /chat",
        "POST /chat/messages"
      ],
      "description": "GET chat thread and POST chat messages scoped to deckId; include optional slideId.",
      "comments": [],
      "request_approval": null,
      "created_at": "2026-02-26T23:20:00Z",
      "updated_at": "2026-02-26T23:20:00Z",
      "created_by": "sentinel",
      "updated_by": "sentinel"
    },
    {
      "id": "TASK-0039",
      "title": "TS-API.1 Implement templates endpoint and validation",
      "status": "Backlog",
      "owner": "sentinel",
      "due_date": null,
      "priority": "P1",
      "tags": [
        "task",
        "epic:EP-B",
        "api"
      ],
      "linked_refs": [
        "GET /api/presentation-studio/templates"
      ],
      "description": "GET /api/presentation-studio/templates returns >=8 templates with slotsSchema and constraintsDefaults; reject invalid templateId assignments.",
      "comments": [],
      "request_approval": null,
      "created_at": "2026-02-26T23:20:00Z",
      "updated_at": "2026-02-26T23:20:00Z",
      "created_by": "sentinel",
      "updated_by": "sentinel"
    },
    {
      "id": "TASK-0040",
      "title": "TS-QA.1 Enforce QA blocking flags on export/publish",
      "status": "Backlog",
      "owner": "sentinel",
      "due_date": null,
      "priority": "P1",
      "tags": [
        "task",
        "qa",
        "guardrails"
      ],
      "linked_refs": [
        "qa_rules"
      ],
      "description": "Block export when OVERFLOW or INCONSISTENT_HEADER flags exist; add auto-fix trigger.",
      "comments": [],
      "request_approval": null,
      "created_at": "2026-02-26T23:20:00Z",
      "updated_at": "2026-02-26T23:20:00Z",
      "created_by": "sentinel",
      "updated_by": "sentinel"
    },
    {
      "id": "TASK-0041",
      "title": "EP-H Pipeline Run Endpoint Hardening",
      "status": "Backlog",
      "owner": "sentinel",
      "due_date": null,
      "priority": "P0",
      "tags": [
        "epic",
        "pipeline",
        "decomposition"
      ],
      "linked_refs": [
        "TASK-0032"
      ],
      "description": "Decompose TS-A3.1 into atomic steps before implementation to avoid oversized changes.",
      "comments": [],
      "request_approval": null,
      "created_at": "2026-02-27T23:24:00Z",
      "updated_at": "2026-02-27T23:24:00Z",
      "created_by": "sentinel",
      "updated_by": "sentinel"
    },
    {
      "id": "TASK-0042",
      "title": "US-H1 Validate request contract for pipeline run",
      "status": "Backlog",
      "owner": "sentinel",
      "due_date": null,
      "priority": "P0",
      "tags": [
        "story",
        "epic:EP-H"
      ],
      "linked_refs": [
        "TASK-0032"
      ],
      "description": "Define and enforce scope/stages/slideId validation for pipeline run endpoint.",
      "comments": [],
      "request_approval": null,
      "created_at": "2026-02-27T23:24:00Z",
      "updated_at": "2026-02-27T23:24:00Z",
      "created_by": "sentinel",
      "updated_by": "sentinel"
    },
    {
      "id": "TASK-0043",
      "title": "TS-H1.1 Implement POST /pipeline/run request validation + runId creation",
      "status": "In Progress",
      "owner": "sentinel",
      "due_date": null,
      "priority": "P0",
      "tags": [
        "task",
        "story:US-H1",
        "epic:EP-H"
      ],
      "linked_refs": [
        "/api/presentation-studio/decks/{deckId}/pipeline/run"
      ],
      "description": "Create atomic first slice: validate input + create persisted run record with started status.",
      "comments": [],
      "request_approval": null,
      "created_at": "2026-02-27T23:24:00Z",
      "updated_at": "2026-02-27T23:24:00Z",
      "created_by": "sentinel",
      "updated_by": "sentinel"
    },
    {
      "id": "TASK-0044",
      "title": "TS-H1.2 Persist per-stage status transitions",
      "status": "Backlog",
      "owner": "sentinel",
      "due_date": null,
      "priority": "P0",
      "tags": [
        "task",
        "story:US-H1",
        "epic:EP-H"
      ],
      "linked_refs": [
        "pipeline.status"
      ],
      "description": "Add stage-by-stage status persistence (plan/draft/critique/rewrite/render/qa).",
      "comments": [],
      "request_approval": null,
      "created_at": "2026-02-27T23:24:00Z",
      "updated_at": "2026-02-27T23:24:00Z",
      "created_by": "sentinel",
      "updated_by": "sentinel"
    }
  ]
}
